playlist_along/__init__.py
playlist_along/__main__.py
playlist_along/_utils.py
playlist_along/cli.py
playlist_along/commands/__init__.py
playlist_along/commands/convert.py
playlist_along/commands/create.py
playlist_along/commands/display.py
playlist_along/commands/inject.py
playlist_along/playlist.py
playlist_along/py.typed
playlist_along-2024.8.8.dist-info/LICENSE.rst
playlist_along-2024.8.8.dist-info/METADATA
playlist_along-2024.8.8.dist-info/WHEEL
playlist_along-2024.8.8.dist-info/entry_points.txt
playlist_along-2024.8.8.dist-info/RECORD
