Metadata-Version: 2.1
Name: playlist-along
Version: 2024.8.8
Summary: Python CLI app for M3U playlists conversion and processing
Home-page: https://github.com/hotenov/playlist-along
License: MIT
Author: Artem Hotenov
Author-email: qa@hotenov.com
Requires-Python: >=3.11,<4.0
Classifier: Development Status :: 4 - Beta
Classifier: License :: OSI Approved :: MIT License
Classifier: Programming Language :: Python :: 3
Classifier: Programming Language :: Python :: 3.11
Classifier: Programming Language :: Python :: 3.12
Classifier: Programming Language :: Python :: 3.10
Classifier: Programming Language :: Python :: 3.9
Requires-Dist: charset-normalizer (>=1.3.9,<4.0.0)
Requires-Dist: click (>=8.0.4,<9.0.0)
Requires-Dist: mutagen (>=1.45.1,<2.0.0)
Requires-Dist: natsort (>=7.1.1,<9.0.0)
Requires-Dist: single-source (>=0.2,<0.4)
Project-URL: Changelog, https://github.com/hotenov/playlist-along/releases
Project-URL: Documentation, https://playlist-along.readthedocs.io
Project-URL: Repository, https://github.com/hotenov/playlist-along
